setup.py
memodules/__init__.py
memodules.egg-info/PKG-INFO
memodules.egg-info/SOURCES.txt
memodules.egg-info/dependency_links.txt
memodules.egg-info/top_level.txt
memodules/alphabet_to_integer/AlphabetToInteger.py
memodules/alphabet_to_integer/__init__.py
memodules/cr_exchange_lib/__init__.py
memodules/cr_exchange_lib/crExchangeLib.py
memodules/decorators/__init__.py
memodules/decorators/debug_dec.py
memodules/error_lib/ErrorLib.py
memodules/error_lib/__init__.py
memodules/log/__init__.py
memodules/log/log.py
memodules/xl_for_python/Python_xlTypeLib_Addin.py
memodules/xl_for_python/__init__.py